[
  {
    "FrameNumber": 0,
    "Balls": []
  },
  {
    "FrameNumber": 1,
    "Balls": []
  },
  {
    "FrameNumber": 2,
    "Balls": [
      {
        "Tag": 0,
        "Position": {
          "X": 122,
          "Y": 1000
        },
        "BoundingBox": {
          "Width": 103,
          "Height": 83
        }
      }
    ]
  },
  {
    "FrameNumber": 3,
    "Balls": [
      {
        "Tag": 0,
        "Position": {
          "X": 216,
          "Y": 876
        },
        "BoundingBox": {
          "Width": 97,
          "Height": 85
        }
      }
    ]
  },
  {
    "FrameNumber": 4,
    "Balls": [
      {
        "Tag": 0,
        "Position": {
          "X": 314,
          "Y": 766
        },
        "BoundingBox": {
          "Width": 99,
          "Height": 86
        }
      },
      {
        "Tag": 1,
        "Position": {
          "X": 1836,
          "Y": 353
        },
        "BoundingBox": {
          "Width": 110,
          "Height": 94
        }
      }
    ]
  },
  {
    "FrameNumber": 5,
    "Balls": [
      {
        "Tag": 0,
        "Position": {
          "X": 417,
          "Y": 673
        },
        "BoundingBox": {
          "Width": 103,
          "Height": 95
        }
      },
      {
        "Tag": 1,
        "Position": {
          "X": 416,
          "Y": 671
        },
        "BoundingBox": {
          "Width": 95,
          "Height": 90
        }
      }
    ]
  },
  {
    "FrameNumber": 6,
    "Balls": [
      {
        "Tag": 0,
        "Position": {
          "X": 520,
          "Y": 592
        },
        "BoundingBox": {
          "Width": 97,
          "Height": 89
        }
      }
    ]
  },
  {
    "FrameNumber": 7,
    "Balls": [
      {
        "Tag": 0,
        "Position": {
          "X": 622,
          "Y": 526
        },
        "BoundingBox": {
          "Width": 92,
          "Height": 91
        }
      }
    ]
  },
  {
    "FrameNumber": 8,
    "Balls": [
      {
        "Tag": 0,
        "Position": {
          "X": 732,
          "Y": 478
        },
        "BoundingBox": {
          "Width": 97,
          "Height": 97
        }
      }
    ]
  },
  {
    "FrameNumber": 9,
    "Balls": [
      {
        "Tag": 0,
        "Position": {
          "X": 846,
          "Y": 449
        },
        "BoundingBox": {
          "Width": 109,
          "Height": 100
        }
      }
    ]
  },
  {
    "FrameNumber": 10,
    "Balls": [
      {
        "Tag": 0,
        "Position": {
          "X": 958,
          "Y": 428
        },
        "BoundingBox": {
          "Width": 101,
          "Height": 92
        }
      }
    ]
  },
  {
    "FrameNumber": 11,
    "Balls": [
      {
        "Tag": 0,
        "Position": {
          "X": 1072,
          "Y": 432
        },
        "BoundingBox": {
          "Width": 97,
          "Height": 101
        }
      }
    ]
  },
  {
    "FrameNumber": 12,
    "Balls": [
      {
        "Tag": 0,
        "Position": {
          "X": 1190,
          "Y": 456
        },
        "BoundingBox": {
          "Width": 99,
          "Height": 103
        }
      }
    ]
  },
  {
    "FrameNumber": 13,
    "Balls": [
      {
        "Tag": 0,
        "Position": {
          "X": 1310,
          "Y": 494
        },
        "BoundingBox": {
          "Width": 103,
          "Height": 103
        }
      }
    ]
  },
  {
    "FrameNumber": 14,
    "Balls": [
      {
        "Tag": 0,
        "Position": {
          "X": 1427,
          "Y": 551
        },
        "BoundingBox": {
          "Width": 106,
          "Height": 104
        }
      }
    ]
  },
  {
    "FrameNumber": 15,
    "Balls": [
      {
        "Tag": 0,
        "Position": {
          "X": 1548,
          "Y": 632
        },
        "BoundingBox": {
          "Width": 103,
          "Height": 110
        }
      }
    ]
  },
  {
    "FrameNumber": 16,
    "Balls": [
      {
        "Tag": 0,
        "Position": {
          "X": 1670,
          "Y": 734
        },
        "BoundingBox": {
          "Width": 102,
          "Height": 111
        }
      }
    ]
  },
  {
    "FrameNumber": 17,
    "Balls": [
      {
        "Tag": 0,
        "Position": {
          "X": 1796,
          "Y": 856
        },
        "BoundingBox": {
          "Width": 109,
          "Height": 107
        }
      }
    ]
  },
  {
    "FrameNumber": 18,
    "Balls": [
      {
        "Tag": 0,
        "Position": {
          "X": 960,
          "Y": 540
        },
        "BoundingBox": {
          "Width": 80,
          "Height": 80
        }
      }
    ]
  },
  {
    "FrameNumber": 19,
    "Balls": []
  },
  {
    "FrameNumber": 20,
    "Balls": null
  }
]